pybuilder_header_plugin-0.1.0.dist-info/WHEEL
pybuilder_header_plugin-0.1.0.dist-info/metadata.json
pybuilder_header_plugin-0.1.0.dist-info/METADATA
pybuilder_header_plugin-0.1.0.dist-info/zip-safe
pybuilder_header_plugin-0.1.0.dist-info/entry_points.txt
pybuilder_header_plugin-0.1.0.dist-info/RECORD
pybuilder_header_plugin-0.1.0.dist-info/DESCRIPTION.rst
pybuilder_header_plugin-0.1.0.dist-info/top_level.txt
pybuilder_header_plugin/__init__.py
