Metadata-Version: 1.1
Name: pybuilder_header_plugin
Version: 0.1.0
Summary: PyBuilder Header Plugin
Home-page: https://github.com/cowst/pybuilder_header_plugin
Author: Diego Costantini, Michael Gruber
Author-email: diego.costantini@gmail.com, aelgru@gmail.com
License: Apache License, Version 2.0
Platform: UNKNOWN
Classifier: Development Status :: 4 - Beta
Classifier: Environment :: Console
Classifier: Intended Audience :: Developers
Classifier: License :: OSI Approved :: Apache Software License
Classifier: Programming Language :: Python
Classifier: Programming Language :: Python :: 2
Classifier: Programming Language :: Python :: 2.7
Classifier: Programming Language :: Python :: 3
Classifier: Programming Language :: Python :: 3.2
Classifier: Programming Language :: Python :: 3.3
Classifier: Programming Language :: Python :: 3.4
